{
  "-22,-10": {
    "SourceVersionHash": "cXKuc2GvvG8vwUJIfxntGGgseq0=",
    "VersionHash": "GfKc+m0U585viCyJ5DgZIf2LFos="
  },
  "-21,-10": {
    "SourceVersionHash": "cXKuc2GvvG8vwUJIfxntGGgseq0=",
    "VersionHash": "GfKc+m0U585viCyJ5DgZIf2LFos="
  },
  "-21,-9": {
    "SourceVersionHash": "7jyRPvg/HbMnWNH1Wa0qI0XM1Gg=",
    "VersionHash": "5epzV8vBsWVN5ETimog/gWBCbXs="
  },
  "-23,-8": {
    "SourceVersionHash": "mDUMEQKMaD0mgoXPajdlNgfo0Zk=",
    "VersionHash": "5epzV8vBsWVN5ETimog/gWBCbXs="
  },
  "-23,-7": {
    "SourceVersionHash": "lUb1eKCREX7KfMAAxLGNK1hoBVA=",
    "VersionHash": "0seColCnz+V09T7V74FY3mJkQww="
  },
  "-21,-7": {
    "SourceVersionHash": "lUb1eKCREX7KfMAAxLGNK1hoBVA=",
    "VersionHash": "0seColCnz+V09T7V74FY3mJkQww="
  },
  "-22,-6": {
    "SourceVersionHash": "QjXsFYUIvuPjezEp1fNsldwKvNg=",
    "VersionHash": "0seColCnz+V09T7V74FY3mJkQww="
  },
  "-21,-6": {
    "SourceVersionHash": "QjXsFYUIvuPjezEp1fNsldwKvNg=",
    "VersionHash": "0seColCnz+V09T7V74FY3mJkQww="
  },
  "-23,-5": {
    "SourceVersionHash": "mS6ClYMoLQghrukBUb3mLX8unNM=",
    "VersionHash": "+QyGevAJFUddiSoaUATXozH3ZvI="
  },
  "-21,-5": {
    "SourceVersionHash": "HEfeAQv5zLm97Cgr/moUDsEaoL4=",
    "VersionHash": "+QyGevAJFUddiSoaUATXozH3ZvI="
  },
  "-23,-4": {
    "SourceVersionHash": "IYwZGmyLdfISAFpqc8kgVimzJG8=",
    "VersionHash": "hVC6sgMUiyh/dM1WWoUIv8pxNN4="
  },
  "-21,-4": {
    "SourceVersionHash": "irLuZgTUS3Bphr+9FpBka2+Yu/g=",
    "VersionHash": "hVC6sgMUiyh/dM1WWoUIv8pxNN4="
  },
  "-23,-3": {
    "SourceVersionHash": "dOVcxrtP8YmPgq+yI5QPVT2TV9s=",
    "VersionHash": "hVC6sgMUiyh/dM1WWoUIv8pxNN4="
  },
  "-21,-2": {
    "SourceVersionHash": "nQKnszD1NIsoja7LzhZMv9hoARY=",
    "VersionHash": "XU0cUQIvlcyoIQ3V17Q45NeYAwU="
  },
  "-23,-1": {
    "SourceVersionHash": "Tirdv1EnNvJz2vS05kTnAgKrYrc=",
    "VersionHash": "22QoWjwDo/a7ol4ZhOW7Mtoybi4="
  },
  "-22,-1": {
    "SourceVersionHash": "Tirdv1EnNvJz2vS05kTnAgKrYrc=",
    "VersionHash": "22QoWjwDo/a7ol4ZhOW7Mtoybi4="
  }
}