{
  "57,116": {
    "SourceVersionHash": "YR3zPTG+ei+1ypPeKQHjtHLapFs=",
    "VersionHash": "X2n3JyAnwwlPdsmVUqAnVF9zyZE="
  },
  "56,117": {
    "SourceVersionHash": "YR3zPTG+ei+1ypPeKQHjtHLapFs=",
    "VersionHash": "X2n3JyAnwwlPdsmVUqAnVF9zyZE="
  },
  "56,116": {
    "SourceVersionHash": "YR3zPTG+ei+1ypPeKQHjtHLapFs=",
    "VersionHash": "X2n3JyAnwwlPdsmVUqAnVF9zyZE="
  },
  "57,117": {
    "SourceVersionHash": "YR3zPTG+ei+1ypPeKQHjtHLapFs=",
    "VersionHash": "X2n3JyAnwwlPdsmVUqAnVF9zyZE="
  },
  "50,117": {
    "SourceVersionHash": "YR3zPTG+ei+1ypPeKQHjtHLapFs=",
    "VersionHash": "RYBamL7O3dZnRGW4Ol6qyixClaQ="
  },
  "51,117": {
    "SourceVersionHash": "YR3zPTG+ei+1ypPeKQHjtHLapFs=",
    "VersionHash": "RYBamL7O3dZnRGW4Ol6qyixClaQ="
  },
  "50,116": {
    "SourceVersionHash": "YR3zPTG+ei+1ypPeKQHjtHLapFs=",
    "VersionHash": "RYBamL7O3dZnRGW4Ol6qyixClaQ="
  },
  "51,116": {
    "SourceVersionHash": "YR3zPTG+ei+1ypPeKQHjtHLapFs=",
    "VersionHash": "RYBamL7O3dZnRGW4Ol6qyixClaQ="
  },
  "53,113": {
    "SourceVersionHash": "YR3zPTG+ei+1ypPeKQHjtHLapFs=",
    "VersionHash": "8GfKqKlBU4hlyu0zj8LgEpH3wZ0="
  },
  "52,112": {
    "SourceVersionHash": "YR3zPTG+ei+1ypPeKQHjtHLapFs=",
    "VersionHash": "8GfKqKlBU4hlyu0zj8LgEpH3wZ0="
  },
  "52,113": {
    "SourceVersionHash": "YR3zPTG+ei+1ypPeKQHjtHLapFs=",
    "VersionHash": "8GfKqKlBU4hlyu0zj8LgEpH3wZ0="
  },
  "53,112": {
    "SourceVersionHash": "YR3zPTG+ei+1ypPeKQHjtHLapFs=",
    "VersionHash": "8GfKqKlBU4hlyu0zj8LgEpH3wZ0="
  },
  "57,111": {
    "SourceVersionHash": "YR3zPTG+ei+1ypPeKQHjtHLapFs=",
    "VersionHash": "mIgvafsUGEhob6D8MsNc2zI8aMQ="
  },
  "57,110": {
    "SourceVersionHash": "YR3zPTG+ei+1ypPeKQHjtHLapFs=",
    "VersionHash": "mIgvafsUGEhob6D8MsNc2zI8aMQ="
  },
  "56,111": {
    "SourceVersionHash": "YR3zPTG+ei+1ypPeKQHjtHLapFs=",
    "VersionHash": "mIgvafsUGEhob6D8MsNc2zI8aMQ="
  },
  "56,110": {
    "SourceVersionHash": "YR3zPTG+ei+1ypPeKQHjtHLapFs=",
    "VersionHash": "mIgvafsUGEhob6D8MsNc2zI8aMQ="
  }
}