{
  "56,-49": {
    "SourceVersionHash": "8SnGj5eEXQRbL2qQKqObHL94S0E=",
    "VersionHash": "SNaqRJ2k2UjRNzp0LP56vXh5yu4="
  },
  "57,-49": {
    "SourceVersionHash": "8SnGj5eEXQRbL2qQKqObHL94S0E=",
    "VersionHash": "SNaqRJ2k2UjRNzp0LP56vXh5yu4="
  },
  "57,-50": {
    "SourceVersionHash": "8SnGj5eEXQRbL2qQKqObHL94S0E=",
    "VersionHash": "SNaqRJ2k2UjRNzp0LP56vXh5yu4="
  },
  "56,-50": {
    "SourceVersionHash": "8SnGj5eEXQRbL2qQKqObHL94S0E=",
    "VersionHash": "ychT7FKmo32eFMcMDjnxs6wi2t0="
  },
  "56,-46": {
    "SourceVersionHash": "8SnGj5eEXQRbL2qQKqObHL94S0E=",
    "VersionHash": "+AWgGuLikyVgH3VYV/AasadTiUw="
  },
  "56,-45": {
    "SourceVersionHash": "8SnGj5eEXQRbL2qQKqObHL94S0E=",
    "VersionHash": "+AWgGuLikyVgH3VYV/AasadTiUw="
  },
  "57,-46": {
    "SourceVersionHash": "8SnGj5eEXQRbL2qQKqObHL94S0E=",
    "VersionHash": "+AWgGuLikyVgH3VYV/AasadTiUw="
  },
  "57,-45": {
    "SourceVersionHash": "8SnGj5eEXQRbL2qQKqObHL94S0E=",
    "VersionHash": "+AWgGuLikyVgH3VYV/AasadTiUw="
  },
  "50,-50": {
    "SourceVersionHash": "ILGrZ/m/Yly7niYxpj6Tw/NMohA=",
    "VersionHash": "htlkWolLYiA3kHZPiwMIvjw2ibo="
  },
  "51,-50": {
    "SourceVersionHash": "ILGrZ/m/Yly7niYxpj6Tw/NMohA=",
    "VersionHash": "htlkWolLYiA3kHZPiwMIvjw2ibo="
  },
  "51,-49": {
    "SourceVersionHash": "ILGrZ/m/Yly7niYxpj6Tw/NMohA=",
    "VersionHash": "htlkWolLYiA3kHZPiwMIvjw2ibo="
  },
  "50,-49": {
    "SourceVersionHash": "ILGrZ/m/Yly7niYxpj6Tw/NMohA=",
    "VersionHash": "htlkWolLYiA3kHZPiwMIvjw2ibo="
  },
  "51,-44": {
    "SourceVersionHash": "ILGrZ/m/Yly7niYxpj6Tw/NMohA=",
    "VersionHash": "VZOXd1NUDOBcBwF5D4IfC98tq34="
  },
  "50,-44": {
    "SourceVersionHash": "ILGrZ/m/Yly7niYxpj6Tw/NMohA=",
    "VersionHash": "VZOXd1NUDOBcBwF5D4IfC98tq34="
  },
  "50,-43": {
    "SourceVersionHash": "ILGrZ/m/Yly7niYxpj6Tw/NMohA=",
    "VersionHash": "VZOXd1NUDOBcBwF5D4IfC98tq34="
  },
  "51,-43": {
    "SourceVersionHash": "ILGrZ/m/Yly7niYxpj6Tw/NMohA=",
    "VersionHash": "VZOXd1NUDOBcBwF5D4IfC98tq34="
  }
}