{
  "-60,-4": {
    "SourceVersionHash": "Dvnq/upDGPkltHao0R2vV+5Pc/w=",
    "VersionHash": "sF7P7Bl6ZRqQrAmYxzFvNH1lVNs="
  },
  "-53,-4": {
    "SourceVersionHash": "Dvnq/upDGPkltHao0R2vV+5Pc/w=",
    "VersionHash": "q/McSHxeghslt7M/ydDiXCfARWQ="
  },
  "-54,-4": {
    "SourceVersionHash": "Dvnq/upDGPkltHao0R2vV+5Pc/w=",
    "VersionHash": "q/McSHxeghslt7M/ydDiXCfARWQ="
  },
  "-54,-3": {
    "SourceVersionHash": "Dvnq/upDGPkltHao0R2vV+5Pc/w=",
    "VersionHash": "q/McSHxeghslt7M/ydDiXCfARWQ="
  },
  "-53,-3": {
    "SourceVersionHash": "Dvnq/upDGPkltHao0R2vV+5Pc/w=",
    "VersionHash": "q/McSHxeghslt7M/ydDiXCfARWQ="
  },
  "-58,-8": {
    "SourceVersionHash": "Dvnq/upDGPkltHao0R2vV+5Pc/w=",
    "VersionHash": "XLJJ1he3ocC+Slv0vZjRGzMO4Uk="
  },
  "-57,-7": {
    "SourceVersionHash": "Dvnq/upDGPkltHao0R2vV+5Pc/w=",
    "VersionHash": "XLJJ1he3ocC+Slv0vZjRGzMO4Uk="
  },
  "-57,-8": {
    "SourceVersionHash": "Dvnq/upDGPkltHao0R2vV+5Pc/w=",
    "VersionHash": "XLJJ1he3ocC+Slv0vZjRGzMO4Uk="
  },
  "-58,-7": {
    "SourceVersionHash": "Dvnq/upDGPkltHao0R2vV+5Pc/w=",
    "VersionHash": "XLJJ1he3ocC+Slv0vZjRGzMO4Uk="
  },
  "-53,-9": {
    "SourceVersionHash": "Dvnq/upDGPkltHao0R2vV+5Pc/w=",
    "VersionHash": "aVlmgt5QS6cgrFotophL8fsttqc="
  },
  "-54,-10": {
    "SourceVersionHash": "Dvnq/upDGPkltHao0R2vV+5Pc/w=",
    "VersionHash": "aVlmgt5QS6cgrFotophL8fsttqc="
  },
  "-53,-10": {
    "SourceVersionHash": "Dvnq/upDGPkltHao0R2vV+5Pc/w=",
    "VersionHash": "aVlmgt5QS6cgrFotophL8fsttqc="
  },
  "-54,-9": {
    "SourceVersionHash": "Dvnq/upDGPkltHao0R2vV+5Pc/w=",
    "VersionHash": "aVlmgt5QS6cgrFotophL8fsttqc="
  },
  "-59,-3": {
    "SourceVersionHash": "Dvnq/upDGPkltHao0R2vV+5Pc/w=",
    "VersionHash": "wEOSa//aNyTsMfs4rXXO4iuKPu4="
  },
  "-60,-3": {
    "SourceVersionHash": "Dvnq/upDGPkltHao0R2vV+5Pc/w=",
    "VersionHash": "wEOSa//aNyTsMfs4rXXO4iuKPu4="
  },
  "-59,-4": {
    "SourceVersionHash": "Dvnq/upDGPkltHao0R2vV+5Pc/w=",
    "VersionHash": "wEOSa//aNyTsMfs4rXXO4iuKPu4="
  }
}