{
  "9,6": {
    "SourceVersionHash": "q5uL8fGlY+mMfH+a34xzOsFBViM=",
    "VersionHash": "Kfj3KMqNI8MdnflICe7arhx0ANI="
  },
  "3,0": {
    "SourceVersionHash": "NKmdVYKV0vrxj3ms2fc4fENNuR4=",
    "VersionHash": "o7o6eo2UBKHskHbMyGNqoo7Zgkg="
  },
  "4,0": {
    "SourceVersionHash": "NKmdVYKV0vrxj3ms2fc4fENNuR4=",
    "VersionHash": "j1zR9ZoUEfpw1MqYqxexrd61hbI="
  },
  "5,0": {
    "SourceVersionHash": "NKmdVYKV0vrxj3ms2fc4fENNuR4=",
    "VersionHash": "o7o6eo2UBKHskHbMyGNqoo7Zgkg="
  },
  "6,0": {
    "SourceVersionHash": "2mRdrpnglY6h61RBYtXdqjs8nN0=",
    "VersionHash": "BHIRqUGfrPFva+vaqo21Bt/Np8I="
  },
  "7,6": {
    "SourceVersionHash": "eUc79VIn6GXjcy8uPKbGKx/nEJM=",
    "VersionHash": "Tbprg6vaYOUGYRA+HxteOs4IzhI="
  },
  "8,6": {
    "SourceVersionHash": "q5uL8fGlY+mMfH+a34xzOsFBViM=",
    "VersionHash": "Tbprg6vaYOUGYRA+HxteOs4IzhI="
  },
  "5,6": {
    "SourceVersionHash": "46oVFZetdrMN6MiB/DmZxMhK1k0=",
    "VersionHash": "Tbprg6vaYOUGYRA+HxteOs4IzhI="
  },
  "6,6": {
    "SourceVersionHash": "eUc79VIn6GXjcy8uPKbGKx/nEJM=",
    "VersionHash": "Tbprg6vaYOUGYRA+HxteOs4IzhI="
  },
  "4,6": {
    "SourceVersionHash": "46oVFZetdrMN6MiB/DmZxMhK1k0=",
    "VersionHash": "Tbprg6vaYOUGYRA+HxteOs4IzhI="
  },
  "3,6": {
    "SourceVersionHash": "46oVFZetdrMN6MiB/DmZxMhK1k0=",
    "VersionHash": "Tbprg6vaYOUGYRA+HxteOs4IzhI="
  },
  "4,5": {
    "SourceVersionHash": "46oVFZetdrMN6MiB/DmZxMhK1k0=",
    "VersionHash": "Tbprg6vaYOUGYRA+HxteOs4IzhI="
  },
  "5,5": {
    "SourceVersionHash": "46oVFZetdrMN6MiB/DmZxMhK1k0=",
    "VersionHash": "Tbprg6vaYOUGYRA+HxteOs4IzhI="
  },
  "3,5": {
    "SourceVersionHash": "XGYv3Tw3c+B04RSdpIa9DUiw760=",
    "VersionHash": "q5GA1GOBzkc3UpW9ZUZSWcbBc9c="
  },
  "9,7": {
    "SourceVersionHash": "q5uL8fGlY+mMfH+a34xzOsFBViM=",
    "VersionHash": "91qe2VzvmOKsJ5MzEflFUuSsxxQ="
  },
  "9,8": {
    "SourceVersionHash": "CjgTrsWmu8sPwK16TwVFhCtFVH8=",
    "VersionHash": "zWplC13xYVBz3aNCBga8pKKHbGE="
  },
  "7,7": {
    "SourceVersionHash": "eUc79VIn6GXjcy8uPKbGKx/nEJM=",
    "VersionHash": "ZuFePcfGJuXnWjQKFYvmaJKAbZk="
  },
  "8,7": {
    "SourceVersionHash": "q5uL8fGlY+mMfH+a34xzOsFBViM=",
    "VersionHash": "ZuFePcfGJuXnWjQKFYvmaJKAbZk="
  },
  "7,8": {
    "SourceVersionHash": "CjgTrsWmu8sPwK16TwVFhCtFVH8=",
    "VersionHash": "ZuFePcfGJuXnWjQKFYvmaJKAbZk="
  },
  "8,8": {
    "SourceVersionHash": "CjgTrsWmu8sPwK16TwVFhCtFVH8=",
    "VersionHash": "ZuFePcfGJuXnWjQKFYvmaJKAbZk="
  },
  "6,7": {
    "SourceVersionHash": "eUc79VIn6GXjcy8uPKbGKx/nEJM=",
    "VersionHash": "b38RZQK/nOHI7rpnTwOAt5xL+Xw="
  },
  "5,7": {
    "SourceVersionHash": "46oVFZetdrMN6MiB/DmZxMhK1k0=",
    "VersionHash": "b38RZQK/nOHI7rpnTwOAt5xL+Xw="
  },
  "6,8": {
    "SourceVersionHash": "CjgTrsWmu8sPwK16TwVFhCtFVH8=",
    "VersionHash": "b38RZQK/nOHI7rpnTwOAt5xL+Xw="
  },
  "5,8": {
    "SourceVersionHash": "CjgTrsWmu8sPwK16TwVFhCtFVH8=",
    "VersionHash": "b38RZQK/nOHI7rpnTwOAt5xL+Xw="
  },
  "4,7": {
    "SourceVersionHash": "46oVFZetdrMN6MiB/DmZxMhK1k0=",
    "VersionHash": "HHV5mFaCjSCLC9tlK+rn39m2VyE="
  },
  "3,7": {
    "SourceVersionHash": "46oVFZetdrMN6MiB/DmZxMhK1k0=",
    "VersionHash": "HHV5mFaCjSCLC9tlK+rn39m2VyE="
  },
  "4,8": {
    "SourceVersionHash": "CjgTrsWmu8sPwK16TwVFhCtFVH8=",
    "VersionHash": "HHV5mFaCjSCLC9tlK+rn39m2VyE="
  },
  "3,8": {
    "SourceVersionHash": "CjgTrsWmu8sPwK16TwVFhCtFVH8=",
    "VersionHash": "HHV5mFaCjSCLC9tlK+rn39m2VyE="
  },
  "9,3": {
    "SourceVersionHash": "Qgyi8n4h6GtaZk6pzI4kijWdlIE=",
    "VersionHash": "cFsMjn+QKAOtubA0p2fpC4USIgI="
  },
  "9,2": {
    "SourceVersionHash": "Qgyi8n4h6GtaZk6pzI4kijWdlIE=",
    "VersionHash": "cFsMjn+QKAOtubA0p2fpC4USIgI="
  },
  "9,9": {
    "SourceVersionHash": "CjgTrsWmu8sPwK16TwVFhCtFVH8=",
    "VersionHash": "RcF3RdzgrseQqaQ8aYFEbFA5pg8="
  },
  "1,0": {
    "SourceVersionHash": "9Q88hyN12De3yn/uCCjKBMhNNms=",
    "VersionHash": "0gov8ZJLRDeaxRLals7r+PnyI9A="
  },
  "2,0": {
    "SourceVersionHash": "NKmdVYKV0vrxj3ms2fc4fENNuR4=",
    "VersionHash": "0gov8ZJLRDeaxRLals7r+PnyI9A="
  },
  "2,1": {
    "SourceVersionHash": "NKmdVYKV0vrxj3ms2fc4fENNuR4=",
    "VersionHash": "ES2oxQfIvYZtNbjDPYFKJ1TpLd8="
  },
  "1,2": {
    "SourceVersionHash": "CjgTrsWmu8sPwK16TwVFhCtFVH8=",
    "VersionHash": "72Q8SO+wZMsiQcXwXeB3QhiiRvs="
  },
  "1,1": {
    "SourceVersionHash": "9Q88hyN12De3yn/uCCjKBMhNNms=",
    "VersionHash": "0gov8ZJLRDeaxRLals7r+PnyI9A="
  },
  "2,4": {
    "SourceVersionHash": "XGYv3Tw3c+B04RSdpIa9DUiw760=",
    "VersionHash": "1aX868Ng2bKQzh0Z0QEpczXiqiA="
  },
  "1,4": {
    "SourceVersionHash": "CjgTrsWmu8sPwK16TwVFhCtFVH8=",
    "VersionHash": "juq8MKRd88upUyvRmKwAuYNTnqw="
  },
  "1,3": {
    "SourceVersionHash": "CjgTrsWmu8sPwK16TwVFhCtFVH8=",
    "VersionHash": "juq8MKRd88upUyvRmKwAuYNTnqw="
  },
  "0,1": {
    "SourceVersionHash": "9Q88hyN12De3yn/uCCjKBMhNNms=",
    "VersionHash": "p3IPqT79NggbmTvscEZkVtAuVkE="
  },
  "0,2": {
    "SourceVersionHash": "CjgTrsWmu8sPwK16TwVFhCtFVH8=",
    "VersionHash": "qJvNlvfzgOVxusa0Hxa15ebTa3c="
  },
  "4,1": {
    "SourceVersionHash": "NKmdVYKV0vrxj3ms2fc4fENNuR4=",
    "VersionHash": "ES2oxQfIvYZtNbjDPYFKJ1TpLd8="
  },
  "3,1": {
    "SourceVersionHash": "NKmdVYKV0vrxj3ms2fc4fENNuR4=",
    "VersionHash": "0gov8ZJLRDeaxRLals7r+PnyI9A="
  },
  "4,2": {
    "SourceVersionHash": "YqLLX7gcmTkfyQMJ5sw0E4Q8pNA=",
    "VersionHash": "qJvNlvfzgOVxusa0Hxa15ebTa3c="
  },
  "5,4": {
    "SourceVersionHash": "46oVFZetdrMN6MiB/DmZxMhK1k0=",
    "VersionHash": "YyELw1/Y/+LvEfau/4kswG9rdhI="
  },
  "3,4": {
    "SourceVersionHash": "XGYv3Tw3c+B04RSdpIa9DUiw760=",
    "VersionHash": "q5GA1GOBzkc3UpW9ZUZSWcbBc9c="
  },
  "6,3": {
    "SourceVersionHash": "GilZvCzedP2QX+GnMfqiDD37O2A=",
    "VersionHash": "YyELw1/Y/+LvEfau/4kswG9rdhI="
  },
  "8,3": {
    "SourceVersionHash": "Qgyi8n4h6GtaZk6pzI4kijWdlIE=",
    "VersionHash": "YyELw1/Y/+LvEfau/4kswG9rdhI="
  },
  "4,3": {
    "SourceVersionHash": "YqLLX7gcmTkfyQMJ5sw0E4Q8pNA=",
    "VersionHash": "YyELw1/Y/+LvEfau/4kswG9rdhI="
  },
  "7,3": {
    "SourceVersionHash": "GilZvCzedP2QX+GnMfqiDD37O2A=",
    "VersionHash": "YyELw1/Y/+LvEfau/4kswG9rdhI="
  },
  "4,4": {
    "SourceVersionHash": "46oVFZetdrMN6MiB/DmZxMhK1k0=",
    "VersionHash": "YyELw1/Y/+LvEfau/4kswG9rdhI="
  },
  "5,3": {
    "SourceVersionHash": "YqLLX7gcmTkfyQMJ5sw0E4Q8pNA=",
    "VersionHash": "YyELw1/Y/+LvEfau/4kswG9rdhI="
  },
  "7,2": {
    "SourceVersionHash": "GilZvCzedP2QX+GnMfqiDD37O2A=",
    "VersionHash": "YyELw1/Y/+LvEfau/4kswG9rdhI="
  },
  "8,2": {
    "SourceVersionHash": "Qgyi8n4h6GtaZk6pzI4kijWdlIE=",
    "VersionHash": "YyELw1/Y/+LvEfau/4kswG9rdhI="
  },
  "7,1": {
    "SourceVersionHash": "2mRdrpnglY6h61RBYtXdqjs8nN0=",
    "VersionHash": "YyELw1/Y/+LvEfau/4kswG9rdhI="
  },
  "6,1": {
    "SourceVersionHash": "2mRdrpnglY6h61RBYtXdqjs8nN0=",
    "VersionHash": "YyELw1/Y/+LvEfau/4kswG9rdhI="
  },
  "6,2": {
    "SourceVersionHash": "GilZvCzedP2QX+GnMfqiDD37O2A=",
    "VersionHash": "YyELw1/Y/+LvEfau/4kswG9rdhI="
  },
  "5,1": {
    "SourceVersionHash": "NKmdVYKV0vrxj3ms2fc4fENNuR4=",
    "VersionHash": "0gov8ZJLRDeaxRLals7r+PnyI9A="
  },
  "5,2": {
    "SourceVersionHash": "YqLLX7gcmTkfyQMJ5sw0E4Q8pNA=",
    "VersionHash": "YyELw1/Y/+LvEfau/4kswG9rdhI="
  },
  "0,3": {
    "SourceVersionHash": "CjgTrsWmu8sPwK16TwVFhCtFVH8=",
    "VersionHash": "hlcGVJwFQCkIbHPHaFS//sLzSuI="
  },
  "0,4": {
    "SourceVersionHash": "CjgTrsWmu8sPwK16TwVFhCtFVH8=",
    "VersionHash": "hlcGVJwFQCkIbHPHaFS//sLzSuI="
  },
  "2,5": {
    "SourceVersionHash": "XGYv3Tw3c+B04RSdpIa9DUiw760=",
    "VersionHash": "9CSHFKJgXtFLE5HfpjHJ+Xmafmw="
  },
  "2,6": {
    "SourceVersionHash": "46oVFZetdrMN6MiB/DmZxMhK1k0=",
    "VersionHash": "RgNh9r2R0ezO9W6RaTlJlyziiHA="
  },
  "1,6": {
    "SourceVersionHash": "CjgTrsWmu8sPwK16TwVFhCtFVH8=",
    "VersionHash": "RgNh9r2R0ezO9W6RaTlJlyziiHA="
  },
  "1,5": {
    "SourceVersionHash": "CjgTrsWmu8sPwK16TwVFhCtFVH8=",
    "VersionHash": "RgNh9r2R0ezO9W6RaTlJlyziiHA="
  },
  "4,9": {
    "SourceVersionHash": "CjgTrsWmu8sPwK16TwVFhCtFVH8=",
    "VersionHash": "bHuZPWgd/L7xhi4M2mKzkRsUErA="
  },
  "3,9": {
    "SourceVersionHash": "CjgTrsWmu8sPwK16TwVFhCtFVH8=",
    "VersionHash": "bHuZPWgd/L7xhi4M2mKzkRsUErA="
  },
  "0,5": {
    "SourceVersionHash": "CjgTrsWmu8sPwK16TwVFhCtFVH8=",
    "VersionHash": "bHuZPWgd/L7xhi4M2mKzkRsUErA="
  },
  "0,6": {
    "SourceVersionHash": "CjgTrsWmu8sPwK16TwVFhCtFVH8=",
    "VersionHash": "bHuZPWgd/L7xhi4M2mKzkRsUErA="
  },
  "2,7": {
    "SourceVersionHash": "46oVFZetdrMN6MiB/DmZxMhK1k0=",
    "VersionHash": "+NlsNqlm0plNecnjFhsRvf7zrYE="
  },
  "1,8": {
    "SourceVersionHash": "CjgTrsWmu8sPwK16TwVFhCtFVH8=",
    "VersionHash": "+NlsNqlm0plNecnjFhsRvf7zrYE="
  },
  "2,8": {
    "SourceVersionHash": "CjgTrsWmu8sPwK16TwVFhCtFVH8=",
    "VersionHash": "+NlsNqlm0plNecnjFhsRvf7zrYE="
  },
  "1,7": {
    "SourceVersionHash": "CjgTrsWmu8sPwK16TwVFhCtFVH8=",
    "VersionHash": "+NlsNqlm0plNecnjFhsRvf7zrYE="
  },
  "1,9": {
    "SourceVersionHash": "CjgTrsWmu8sPwK16TwVFhCtFVH8=",
    "VersionHash": "csp+h7++U0VC5wc5eHZdCjub3lI="
  },
  "2,9": {
    "SourceVersionHash": "CjgTrsWmu8sPwK16TwVFhCtFVH8=",
    "VersionHash": "csp+h7++U0VC5wc5eHZdCjub3lI="
  },
  "0,9": {
    "SourceVersionHash": "CjgTrsWmu8sPwK16TwVFhCtFVH8=",
    "VersionHash": "csp+h7++U0VC5wc5eHZdCjub3lI="
  },
  "0,8": {
    "SourceVersionHash": "CjgTrsWmu8sPwK16TwVFhCtFVH8=",
    "VersionHash": "MXQ+wWYyzPDncu1Ams0sqU+iS9I="
  },
  "0,7": {
    "SourceVersionHash": "CjgTrsWmu8sPwK16TwVFhCtFVH8=",
    "VersionHash": "MXQ+wWYyzPDncu1Ams0sqU+iS9I="
  },
  "0,0": {
    "SourceVersionHash": "9Q88hyN12De3yn/uCCjKBMhNNms=",
    "VersionHash": "xkJTCFcWag+1zQR9xP/tRR9+GLo="
  },
  "7,0": {
    "SourceVersionHash": "2mRdrpnglY6h61RBYtXdqjs8nN0=",
    "VersionHash": "4+MG7hIqr5hd1HWBSEDfwZNJUKc="
  },
  "8,9": {
    "SourceVersionHash": "CjgTrsWmu8sPwK16TwVFhCtFVH8=",
    "VersionHash": "mpX4/zaVSjA+OnY5syQKEGNWeXo="
  },
  "5,9": {
    "SourceVersionHash": "CjgTrsWmu8sPwK16TwVFhCtFVH8=",
    "VersionHash": "mpX4/zaVSjA+OnY5syQKEGNWeXo="
  },
  "7,9": {
    "SourceVersionHash": "CjgTrsWmu8sPwK16TwVFhCtFVH8=",
    "VersionHash": "mpX4/zaVSjA+OnY5syQKEGNWeXo="
  },
  "6,9": {
    "SourceVersionHash": "CjgTrsWmu8sPwK16TwVFhCtFVH8=",
    "VersionHash": "mpX4/zaVSjA+OnY5syQKEGNWeXo="
  }
}