{
  "-30,26": {
    "SourceVersionHash": "9uHPVZ7rK2VKIoiAv7TegZ2/xts=",
    "VersionHash": "UTNQtcIPXRl3FY33C6StWobJ830="
  },
  "-29,26": {
    "SourceVersionHash": "9uHPVZ7rK2VKIoiAv7TegZ2/xts=",
    "VersionHash": "UTNQtcIPXRl3FY33C6StWobJ830="
  },
  "-29,27": {
    "SourceVersionHash": "9uHPVZ7rK2VKIoiAv7TegZ2/xts=",
    "VersionHash": "UTNQtcIPXRl3FY33C6StWobJ830="
  },
  "-30,27": {
    "SourceVersionHash": "9uHPVZ7rK2VKIoiAv7TegZ2/xts=",
    "VersionHash": "UTNQtcIPXRl3FY33C6StWobJ830="
  },
  "-24,26": {
    "SourceVersionHash": "9uHPVZ7rK2VKIoiAv7TegZ2/xts=",
    "VersionHash": "nQlRArkuUy4oE+y7gtthTdP+GEg="
  },
  "-23,26": {
    "SourceVersionHash": "9uHPVZ7rK2VKIoiAv7TegZ2/xts=",
    "VersionHash": "nQlRArkuUy4oE+y7gtthTdP+GEg="
  },
  "-24,27": {
    "SourceVersionHash": "9uHPVZ7rK2VKIoiAv7TegZ2/xts=",
    "VersionHash": "nQlRArkuUy4oE+y7gtthTdP+GEg="
  },
  "-23,27": {
    "SourceVersionHash": "9uHPVZ7rK2VKIoiAv7TegZ2/xts=",
    "VersionHash": "nQlRArkuUy4oE+y7gtthTdP+GEg="
  },
  "-23,21": {
    "SourceVersionHash": "06/dzIrMoUIYe2FWeThBqeP0rAU=",
    "VersionHash": "Mzj+P5nlzhQAilQeUeqRM8RCvYo="
  },
  "-24,21": {
    "SourceVersionHash": "06/dzIrMoUIYe2FWeThBqeP0rAU=",
    "VersionHash": "Mzj+P5nlzhQAilQeUeqRM8RCvYo="
  },
  "-24,20": {
    "SourceVersionHash": "06/dzIrMoUIYe2FWeThBqeP0rAU=",
    "VersionHash": "Mzj+P5nlzhQAilQeUeqRM8RCvYo="
  },
  "-23,20": {
    "SourceVersionHash": "06/dzIrMoUIYe2FWeThBqeP0rAU=",
    "VersionHash": "Mzj+P5nlzhQAilQeUeqRM8RCvYo="
  },
  "-30,20": {
    "SourceVersionHash": "06/dzIrMoUIYe2FWeThBqeP0rAU=",
    "VersionHash": "wEOSa//aNyTsMfs4rXXO4iuKPu4="
  },
  "-30,21": {
    "SourceVersionHash": "06/dzIrMoUIYe2FWeThBqeP0rAU=",
    "VersionHash": "wEOSa//aNyTsMfs4rXXO4iuKPu4="
  },
  "-29,21": {
    "SourceVersionHash": "06/dzIrMoUIYe2FWeThBqeP0rAU=",
    "VersionHash": "wEOSa//aNyTsMfs4rXXO4iuKPu4="
  },
  "-29,20": {
    "SourceVersionHash": "06/dzIrMoUIYe2FWeThBqeP0rAU=",
    "VersionHash": "wEOSa//aNyTsMfs4rXXO4iuKPu4="
  }
}