{
  "-10,10": {
    "SourceVersionHash": "PSFcindSp+/i+kBb7Q2ms85VbsI=",
    "VersionHash": "auT0unUO6ovX+Qn/SdW7mvRnQL8="
  },
  "-9,10": {
    "SourceVersionHash": "RFIM/PvhtPYErcsPSkOynYz4X/g=",
    "VersionHash": "auT0unUO6ovX+Qn/SdW7mvRnQL8="
  },
  "-8,10": {
    "SourceVersionHash": "RFIM/PvhtPYErcsPSkOynYz4X/g=",
    "VersionHash": "auT0unUO6ovX+Qn/SdW7mvRnQL8="
  },
  "-6,10": {
    "SourceVersionHash": "PSFcindSp+/i+kBb7Q2ms85VbsI=",
    "VersionHash": "auT0unUO6ovX+Qn/SdW7mvRnQL8="
  },
  "-5,10": {
    "SourceVersionHash": "PSFcindSp+/i+kBb7Q2ms85VbsI=",
    "VersionHash": "auT0unUO6ovX+Qn/SdW7mvRnQL8="
  },
  "-4,10": {
    "SourceVersionHash": "PSFcindSp+/i+kBb7Q2ms85VbsI=",
    "VersionHash": "auT0unUO6ovX+Qn/SdW7mvRnQL8="
  },
  "-2,10": {
    "SourceVersionHash": "PSFcindSp+/i+kBb7Q2ms85VbsI=",
    "VersionHash": "auT0unUO6ovX+Qn/SdW7mvRnQL8="
  },
  "-1,10": {
    "SourceVersionHash": "PSFcindSp+/i+kBb7Q2ms85VbsI=",
    "VersionHash": "auT0unUO6ovX+Qn/SdW7mvRnQL8="
  },
  "-10,11": {
    "SourceVersionHash": "nqRPxvrfSEpV1FKi+5W3W2eJp0U=",
    "VersionHash": "7uYyvZohoX5k0FFw77btHpZWXJI="
  },
  "-9,11": {
    "SourceVersionHash": "nqRPxvrfSEpV1FKi+5W3W2eJp0U=",
    "VersionHash": "7uYyvZohoX5k0FFw77btHpZWXJI="
  },
  "-8,11": {
    "SourceVersionHash": "nqRPxvrfSEpV1FKi+5W3W2eJp0U=",
    "VersionHash": "7uYyvZohoX5k0FFw77btHpZWXJI="
  },
  "-6,11": {
    "SourceVersionHash": "nqRPxvrfSEpV1FKi+5W3W2eJp0U=",
    "VersionHash": "7uYyvZohoX5k0FFw77btHpZWXJI="
  },
  "-5,11": {
    "SourceVersionHash": "nqRPxvrfSEpV1FKi+5W3W2eJp0U=",
    "VersionHash": "7uYyvZohoX5k0FFw77btHpZWXJI="
  },
  "-4,11": {
    "SourceVersionHash": "nqRPxvrfSEpV1FKi+5W3W2eJp0U=",
    "VersionHash": "7uYyvZohoX5k0FFw77btHpZWXJI="
  },
  "-3,11": {
    "SourceVersionHash": "nqRPxvrfSEpV1FKi+5W3W2eJp0U=",
    "VersionHash": "7uYyvZohoX5k0FFw77btHpZWXJI="
  },
  "-10,12": {
    "SourceVersionHash": "Nq68o4dSpcVtoF4SZe3R/8WT7Ic=",
    "VersionHash": "7uYyvZohoX5k0FFw77btHpZWXJI="
  },
  "-9,12": {
    "SourceVersionHash": "Nq68o4dSpcVtoF4SZe3R/8WT7Ic=",
    "VersionHash": "7uYyvZohoX5k0FFw77btHpZWXJI="
  },
  "-7,12": {
    "SourceVersionHash": "Nq68o4dSpcVtoF4SZe3R/8WT7Ic=",
    "VersionHash": "7uYyvZohoX5k0FFw77btHpZWXJI="
  },
  "-6,12": {
    "SourceVersionHash": "Nq68o4dSpcVtoF4SZe3R/8WT7Ic=",
    "VersionHash": "7uYyvZohoX5k0FFw77btHpZWXJI="
  },
  "-2,12": {
    "SourceVersionHash": "Nq68o4dSpcVtoF4SZe3R/8WT7Ic=",
    "VersionHash": "7uYyvZohoX5k0FFw77btHpZWXJI="
  },
  "-1,12": {
    "SourceVersionHash": "Nq68o4dSpcVtoF4SZe3R/8WT7Ic=",
    "VersionHash": "7uYyvZohoX5k0FFw77btHpZWXJI="
  },
  "-5,13": {
    "SourceVersionHash": "n6HFeTOfX7U1okkcZO4qZd4NYSc=",
    "VersionHash": "WCkVo4SNuJ+4KkJi+JMfby3fih0="
  },
  "-4,13": {
    "SourceVersionHash": "f2VYJw+2LEuP/Se+fNSuqf8rgHU=",
    "VersionHash": "WCkVo4SNuJ+4KkJi+JMfby3fih0="
  },
  "-1,13": {
    "SourceVersionHash": "f2VYJw+2LEuP/Se+fNSuqf8rgHU=",
    "VersionHash": "WCkVo4SNuJ+4KkJi+JMfby3fih0="
  },
  "-10,14": {
    "SourceVersionHash": "9menr2pOyGOCBxI1q+jAKWsAScQ=",
    "VersionHash": "WCkVo4SNuJ+4KkJi+JMfby3fih0="
  },
  "-9,14": {
    "SourceVersionHash": "9menr2pOyGOCBxI1q+jAKWsAScQ=",
    "VersionHash": "WCkVo4SNuJ+4KkJi+JMfby3fih0="
  },
  "-7,14": {
    "SourceVersionHash": "9menr2pOyGOCBxI1q+jAKWsAScQ=",
    "VersionHash": "WCkVo4SNuJ+4KkJi+JMfby3fih0="
  },
  "-6,14": {
    "SourceVersionHash": "9menr2pOyGOCBxI1q+jAKWsAScQ=",
    "VersionHash": "WCkVo4SNuJ+4KkJi+JMfby3fih0="
  },
  "-4,14": {
    "SourceVersionHash": "9menr2pOyGOCBxI1q+jAKWsAScQ=",
    "VersionHash": "WCkVo4SNuJ+4KkJi+JMfby3fih0="
  },
  "-3,14": {
    "SourceVersionHash": "9menr2pOyGOCBxI1q+jAKWsAScQ=",
    "VersionHash": "WCkVo4SNuJ+4KkJi+JMfby3fih0="
  },
  "-1,14": {
    "SourceVersionHash": "9menr2pOyGOCBxI1q+jAKWsAScQ=",
    "VersionHash": "l7lwI4xiK8R3Zy0aTASmBbZBkSE="
  },
  "-10,15": {
    "SourceVersionHash": "x7GDKp1CyhdeHNLzuVXE0mes3DQ=",
    "VersionHash": "l7lwI4xiK8R3Zy0aTASmBbZBkSE="
  },
  "-8,15": {
    "SourceVersionHash": "p6NgSEGF0Bj5/mPLASPFPydqqfk=",
    "VersionHash": "l7lwI4xiK8R3Zy0aTASmBbZBkSE="
  },
  "-6,15": {
    "SourceVersionHash": "9menr2pOyGOCBxI1q+jAKWsAScQ=",
    "VersionHash": "l7lwI4xiK8R3Zy0aTASmBbZBkSE="
  },
  "-5,15": {
    "SourceVersionHash": "9menr2pOyGOCBxI1q+jAKWsAScQ=",
    "VersionHash": "l7lwI4xiK8R3Zy0aTASmBbZBkSE="
  },
  "-4,15": {
    "SourceVersionHash": "x7GDKp1CyhdeHNLzuVXE0mes3DQ=",
    "VersionHash": "l7lwI4xiK8R3Zy0aTASmBbZBkSE="
  },
  "-3,15": {
    "SourceVersionHash": "x7GDKp1CyhdeHNLzuVXE0mes3DQ=",
    "VersionHash": "l7lwI4xiK8R3Zy0aTASmBbZBkSE="
  },
  "-1,15": {
    "SourceVersionHash": "x7GDKp1CyhdeHNLzuVXE0mes3DQ=",
    "VersionHash": "l7lwI4xiK8R3Zy0aTASmBbZBkSE="
  },
  "-10,16": {
    "SourceVersionHash": "J+hoatIi+KnDHZNgFmukzUL/TzI=",
    "VersionHash": "ongGfywTB9kIjb3SClOiRFGuxPw="
  },
  "-9,16": {
    "SourceVersionHash": "J+hoatIi+KnDHZNgFmukzUL/TzI=",
    "VersionHash": "ongGfywTB9kIjb3SClOiRFGuxPw="
  },
  "-7,16": {
    "SourceVersionHash": "J+hoatIi+KnDHZNgFmukzUL/TzI=",
    "VersionHash": "ongGfywTB9kIjb3SClOiRFGuxPw="
  },
  "-6,16": {
    "SourceVersionHash": "x7GDKp1CyhdeHNLzuVXE0mes3DQ=",
    "VersionHash": "ongGfywTB9kIjb3SClOiRFGuxPw="
  },
  "-5,16": {
    "SourceVersionHash": "J+hoatIi+KnDHZNgFmukzUL/TzI=",
    "VersionHash": "ongGfywTB9kIjb3SClOiRFGuxPw="
  },
  "-3,16": {
    "SourceVersionHash": "J+hoatIi+KnDHZNgFmukzUL/TzI=",
    "VersionHash": "ongGfywTB9kIjb3SClOiRFGuxPw="
  },
  "-1,16": {
    "SourceVersionHash": "J+hoatIi+KnDHZNgFmukzUL/TzI=",
    "VersionHash": "ongGfywTB9kIjb3SClOiRFGuxPw="
  },
  "-10,17": {
    "SourceVersionHash": "Hz7QNSwkxzi1PyhXUjSw7gj70sk=",
    "VersionHash": "9Lzdbx0yd8sBFcepLFCjWC+Oqds="
  },
  "-9,17": {
    "SourceVersionHash": "Hz7QNSwkxzi1PyhXUjSw7gj70sk=",
    "VersionHash": "9Lzdbx0yd8sBFcepLFCjWC+Oqds="
  },
  "-5,17": {
    "SourceVersionHash": "Hz7QNSwkxzi1PyhXUjSw7gj70sk=",
    "VersionHash": "9Lzdbx0yd8sBFcepLFCjWC+Oqds="
  },
  "-4,17": {
    "SourceVersionHash": "iyy3RSooaJiJfdhJ11O8T0yjII0=",
    "VersionHash": "9Lzdbx0yd8sBFcepLFCjWC+Oqds="
  },
  "-7,18": {
    "SourceVersionHash": "OrJOtNTJl6LATiIOh711KZVOjj4=",
    "VersionHash": "9Lzdbx0yd8sBFcepLFCjWC+Oqds="
  },
  "-6,18": {
    "SourceVersionHash": "Zt0wHpwMDChkm6v+lp3BMSaNYJU=",
    "VersionHash": "9Lzdbx0yd8sBFcepLFCjWC+Oqds="
  },
  "-2,18": {
    "SourceVersionHash": "Zt0wHpwMDChkm6v+lp3BMSaNYJU=",
    "VersionHash": "9Lzdbx0yd8sBFcepLFCjWC+Oqds="
  },
  "-1,18": {
    "SourceVersionHash": "Zt0wHpwMDChkm6v+lp3BMSaNYJU=",
    "VersionHash": "9Lzdbx0yd8sBFcepLFCjWC+Oqds="
  },
  "-10,19": {
    "SourceVersionHash": "MBdSOQQTdf4mEZGrVI0+mSTDfsM=",
    "VersionHash": "9jZy5Mz4dEBYYMvQx1gwz58Vogs="
  },
  "-9,19": {
    "SourceVersionHash": "MBdSOQQTdf4mEZGrVI0+mSTDfsM=",
    "VersionHash": "9jZy5Mz4dEBYYMvQx1gwz58Vogs="
  },
  "-7,19": {
    "SourceVersionHash": "MBdSOQQTdf4mEZGrVI0+mSTDfsM=",
    "VersionHash": "9jZy5Mz4dEBYYMvQx1gwz58Vogs="
  },
  "-5,19": {
    "SourceVersionHash": "MBdSOQQTdf4mEZGrVI0+mSTDfsM=",
    "VersionHash": "9jZy5Mz4dEBYYMvQx1gwz58Vogs="
  },
  "-3,19": {
    "SourceVersionHash": "MBdSOQQTdf4mEZGrVI0+mSTDfsM=",
    "VersionHash": "9jZy5Mz4dEBYYMvQx1gwz58Vogs="
  },
  "-2,19": {
    "SourceVersionHash": "MBdSOQQTdf4mEZGrVI0+mSTDfsM=",
    "VersionHash": "9jZy5Mz4dEBYYMvQx1gwz58Vogs="
  },
  "-1,19": {
    "SourceVersionHash": "MBdSOQQTdf4mEZGrVI0+mSTDfsM=",
    "VersionHash": "9jZy5Mz4dEBYYMvQx1gwz58Vogs="
  }
}