{
  "27,67": {
    "SourceVersionHash": "GnyTGmGBLTFPtW6V6LvMtNtDlRw=",
    "VersionHash": "6aGPU26HGkf6M5ALmcTAdNA7jSw="
  },
  "26,67": {
    "SourceVersionHash": "GnyTGmGBLTFPtW6V6LvMtNtDlRw=",
    "VersionHash": "6aGPU26HGkf6M5ALmcTAdNA7jSw="
  },
  "26,66": {
    "SourceVersionHash": "GnyTGmGBLTFPtW6V6LvMtNtDlRw=",
    "VersionHash": "6aGPU26HGkf6M5ALmcTAdNA7jSw="
  },
  "27,66": {
    "SourceVersionHash": "GnyTGmGBLTFPtW6V6LvMtNtDlRw=",
    "VersionHash": "6aGPU26HGkf6M5ALmcTAdNA7jSw="
  },
  "21,60": {
    "SourceVersionHash": "STq5HyngbK8cB7Nb4LJv1Z60l0s=",
    "VersionHash": "zjZrPdW1nc6PPvlvd95Vlo2a3v0="
  },
  "21,61": {
    "SourceVersionHash": "STq5HyngbK8cB7Nb4LJv1Z60l0s=",
    "VersionHash": "zjZrPdW1nc6PPvlvd95Vlo2a3v0="
  },
  "20,60": {
    "SourceVersionHash": "STq5HyngbK8cB7Nb4LJv1Z60l0s=",
    "VersionHash": "zjZrPdW1nc6PPvlvd95Vlo2a3v0="
  },
  "20,61": {
    "SourceVersionHash": "STq5HyngbK8cB7Nb4LJv1Z60l0s=",
    "VersionHash": "zjZrPdW1nc6PPvlvd95Vlo2a3v0="
  },
  "21,66": {
    "SourceVersionHash": "STq5HyngbK8cB7Nb4LJv1Z60l0s=",
    "VersionHash": "epO48CINHc9GgGn0snkR/4g3LM0="
  },
  "20,67": {
    "SourceVersionHash": "STq5HyngbK8cB7Nb4LJv1Z60l0s=",
    "VersionHash": "epO48CINHc9GgGn0snkR/4g3LM0="
  },
  "20,66": {
    "SourceVersionHash": "STq5HyngbK8cB7Nb4LJv1Z60l0s=",
    "VersionHash": "epO48CINHc9GgGn0snkR/4g3LM0="
  },
  "21,67": {
    "SourceVersionHash": "STq5HyngbK8cB7Nb4LJv1Z60l0s=",
    "VersionHash": "epO48CINHc9GgGn0snkR/4g3LM0="
  },
  "27,63": {
    "SourceVersionHash": "GnyTGmGBLTFPtW6V6LvMtNtDlRw=",
    "VersionHash": "7v/t+y7mXPyuNRfzTnKErnMCi/I="
  },
  "27,62": {
    "SourceVersionHash": "GnyTGmGBLTFPtW6V6LvMtNtDlRw=",
    "VersionHash": "7v/t+y7mXPyuNRfzTnKErnMCi/I="
  },
  "26,63": {
    "SourceVersionHash": "GnyTGmGBLTFPtW6V6LvMtNtDlRw=",
    "VersionHash": "7v/t+y7mXPyuNRfzTnKErnMCi/I="
  },
  "26,62": {
    "SourceVersionHash": "GnyTGmGBLTFPtW6V6LvMtNtDlRw=",
    "VersionHash": "7v/t+y7mXPyuNRfzTnKErnMCi/I="
  }
}