{
  "-17,15": {
    "SourceVersionHash": "iIuhRmyOF6m+xKsx3MJ8JuRX29w=",
    "VersionHash": "YSmo4QmJb6ie6TbmkGIiIUTs1Z4="
  },
  "-19,15": {
    "SourceVersionHash": "no4EJPxPZ3NS7ucwKRuKVsuNFoI=",
    "VersionHash": "Kfj3KMqNI8MdnflICe7arhx0ANI="
  },
  "-18,14": {
    "SourceVersionHash": "iIuhRmyOF6m+xKsx3MJ8JuRX29w=",
    "VersionHash": "9lZKAjxVeiu/5ldb8ebCmmIEUhw="
  },
  "-18,15": {
    "SourceVersionHash": "iIuhRmyOF6m+xKsx3MJ8JuRX29w=",
    "VersionHash": "YSmo4QmJb6ie6TbmkGIiIUTs1Z4="
  },
  "-17,14": {
    "SourceVersionHash": "iIuhRmyOF6m+xKsx3MJ8JuRX29w=",
    "VersionHash": "YSmo4QmJb6ie6TbmkGIiIUTs1Z4="
  },
  "-19,14": {
    "SourceVersionHash": "no4EJPxPZ3NS7ucwKRuKVsuNFoI=",
    "VersionHash": "Kfj3KMqNI8MdnflICe7arhx0ANI="
  },
  "-16,11": {
    "SourceVersionHash": "0+ChanNRhKyR4bftSA1oU3xdkWo=",
    "VersionHash": "dwWr78McMgXKC+f44rmQdyLYqf8="
  },
  "-16,10": {
    "SourceVersionHash": "0+ChanNRhKyR4bftSA1oU3xdkWo=",
    "VersionHash": "dwWr78McMgXKC+f44rmQdyLYqf8="
  },
  "-15,11": {
    "SourceVersionHash": "0+ChanNRhKyR4bftSA1oU3xdkWo=",
    "VersionHash": "dwWr78McMgXKC+f44rmQdyLYqf8="
  },
  "-15,10": {
    "SourceVersionHash": "0+ChanNRhKyR4bftSA1oU3xdkWo=",
    "VersionHash": "dwWr78McMgXKC+f44rmQdyLYqf8="
  },
  "-20,15": {
    "SourceVersionHash": "no4EJPxPZ3NS7ucwKRuKVsuNFoI=",
    "VersionHash": "qJvNlvfzgOVxusa0Hxa15ebTa3c="
  },
  "-20,14": {
    "SourceVersionHash": "no4EJPxPZ3NS7ucwKRuKVsuNFoI=",
    "VersionHash": "+NlsNqlm0plNecnjFhsRvf7zrYE="
  }
}